idewavecore/Assembler.py
idewavecore/__init__.py
idewavecore/constants.py
idewavecore/utils.py
idewavecore/builders/ProxyBuilder.py
idewavecore/builders/ServerBuilder.py
idewavecore/builders/__init__.py
idewavecore/builders/ConfigBuilder/ConfigBuilder.py
idewavecore/builders/ConfigBuilder/__init__.py
idewavecore/builders/ConfigBuilder/ConfigLoader/ConfigLoader.py
idewavecore/builders/ConfigBuilder/ConfigLoader/__init__.py
idewavecore/builders/ConfigBuilder/ConfigLoader/builders/FunctionBuilder.py
idewavecore/builders/ConfigBuilder/ConfigLoader/builders/InfiniteLoopBuilder.py
idewavecore/builders/ConfigBuilder/ConfigLoader/builders/PipeBuilder.py
idewavecore/builders/ConfigBuilder/ConfigLoader/builders/RouterBuilder.py
idewavecore/builders/ConfigBuilder/ConfigLoader/builders/__init__.py
idewavecore/builders/ConfigBuilder/ConfigLoader/mixins/BaseLoaderMixin.py
idewavecore/builders/ConfigBuilder/ConfigLoader/mixins/BuilderLoaderMixin.py
idewavecore/builders/ConfigBuilder/ConfigLoader/mixins/HelperLoaderMixin.py
idewavecore/builders/ConfigBuilder/ConfigLoader/mixins/__init__.py
idewavecore/builders/DBConnectionBuilder/ConnectionMapBuilder.py
idewavecore/builders/DBConnectionBuilder/DBConnectionBuilder.py
idewavecore/builders/DBConnectionBuilder/__init__.py
idewavecore/builders/DBConnectionBuilder/constants.py
idewavecore/crypto/Cypher.py
idewavecore/crypto/HeaderCypher.py
idewavecore/crypto/__init__.py
idewavecore/debug/Logger.py
idewavecore/debug/__init__.py
idewavecore/errors/__init__.py
idewavecore/errors/build.py
idewavecore/errors/storage.py
idewavecore/middlewares/__init__.py
idewavecore/middlewares/crypto.py
idewavecore/middlewares/network.py
idewavecore/middlewares/parsers.py
idewavecore/middlewares/test.py
idewavecore/network/__init__.py
idewavecore/network/connections.py
idewavecore/network/constants.py
idewavecore/network/proxies.py
idewavecore/network/servers.py
idewavecore/parsers/__init__.py
idewavecore/parsers/HttpParser/HttpParser.py
idewavecore-0.0.1.dist-info/LICENSE
idewavecore-0.0.1.dist-info/METADATA
idewavecore-0.0.1.dist-info/WHEEL
idewavecore-0.0.1.dist-info/top_level.txt
idewavecore-0.0.1.dist-info/RECORD
