Metadata-Version: 2.1
Name: idewavecore
Version: 0.0.1
Summary: Framework for creating custom servers
Home-page: https://github.com/idewave/idewavecore
Author: Sergio Ivanuzzo
Author-email: sergio.ivanuzzo@gmail.com
License: Apache license 2.0
Platform: UNKNOWN
Requires-Dist: colorama (==0.4.4)
Requires-Dist: PyYAML (==5.3.1)
Requires-Dist: SQLAlchemy (==1.3.22)
Requires-Dist: websockets (==8.1)
